{
  "login": "Niffler",
  "id": 8172446,
  "node_id": "MDQ6VXNlcjgxNzI0NDY=",
  "avatar_url": "https://avatars.githubusercontent.com/u/8172446?v=4",
  "gravatar_id": "",
  "url": "https://api.github.com/users/Niffler",
  "html_url": "https://github.com/Niffler",
  "followers_url": "https://api.github.com/users/Niffler/followers",
  "following_url": "https://api.github.com/users/Niffler/following{/other_user}",
  "gists_url": "https://api.github.com/users/Niffler/gists{/gist_id}",
  "starred_url": "https://api.github.com/users/Niffler/starred{/owner}{/repo}",
  "subscriptions_url": "https://api.github.com/users/Niffler/subscriptions",
  "organizations_url": "https://api.github.com/users/Niffler/orgs",
  "repos_url": "https://api.github.com/users/Niffler/repos",
  "events_url": "https://api.github.com/users/Niffler/events{/privacy}",
  "received_events_url": "https://api.github.com/users/Niffler/received_events",
  "type": "User",
  "user_view_type": "public",
  "site_admin": false,
  "name": null,
  "company": null,
  "blog": "lpaste.de",
  "location": null,
  "email": null,
  "hireable": null,
  "bio": null,
  "twitter_username": null,
  "public_repos": 4,
  "public_gists": 2,
  "followers": 2,
  "following": 4,
  "created_at": "2014-07-15T18:38:37Z",
  "updated_at": "2024-11-01T09:43:15Z",
  "pronouns": "no_pronouns"
}