{
  "login": "vicluo96",
  "id": 91009762,
  "node_id": "MDQ6VXNlcjkxMDA5NzYy",
  "avatar_url": "https://avatars.githubusercontent.com/u/91009762?v=4",
  "gravatar_id": "",
  "url": "https://api.github.com/users/vicluo96",
  "html_url": "https://github.com/vicluo96",
  "followers_url": "https://api.github.com/users/vicluo96/followers",
  "following_url": "https://api.github.com/users/vicluo96/following{/other_user}",
  "gists_url": "https://api.github.com/users/vicluo96/gists{/gist_id}",
  "starred_url": "https://api.github.com/users/vicluo96/starred{/owner}{/repo}",
  "subscriptions_url": "https://api.github.com/users/vicluo96/subscriptions",
  "organizations_url": "https://api.github.com/users/vicluo96/orgs",
  "repos_url": "https://api.github.com/users/vicluo96/repos",
  "events_url": "https://api.github.com/users/vicluo96/events{/privacy}",
  "received_events_url": "https://api.github.com/users/vicluo96/received_events",
  "type": "User",
  "user_view_type": "public",
  "site_admin": false,
  "name": "Victor Luo",
  "company": null,
  "blog": "",
  "location": "Irvine, CA",
  "email": null,
  "hireable": null,
  "bio": null,
  "twitter_username": null,
  "public_repos": 10,
  "public_gists": 0,
  "followers": 1,
  "following": 0,
  "created_at": "2021-09-19T10:10:59Z",
  "updated_at": "2024-10-28T19:42:44Z",
  "pronouns": "no_pronouns"
}